Metadata-Version: 1.1
Name: morris-counter
Version: 0.1.2
Summary: Memory-efficient probabilistic counter namely Morris Counter
Home-page: https://github.com/ikegami-yukino/morris_counter
Author: Yukino Ikegami
Author-email: yknikgm@gmail.com
License: MIT License
Keywords: counter,probabilistic data structure,approximate counting
Platform: POSIX
Platform: Windows
Platform: Unix
Platform: MacOS
Classifier: Development Status :: 3 - Alpha
Classifier: Intended Audience :: Developers
Classifier: Intended Audience :: Information Technology
Classifier: License :: OSI Approved :: MIT License
Classifier: Programming Language :: Python :: 3.5
Classifier: Programming Language :: Python :: 3.6
Classifier: Programming Language :: Python :: 3.7
